setup.cfg
setup.py
tyrion/__init__.py
tyrion/backprop.py
tyrion/probarray.py
tyrion/train.py
tyrion/utils.py
tyrion.egg-info/PKG-INFO
tyrion.egg-info/SOURCES.txt
tyrion.egg-info/dependency_links.txt
tyrion.egg-info/requires.txt
tyrion.egg-info/top_level.txt