Metadata-Version: 1.1
Name: tyrion
Version: 0.1
Summary: Word Embedding based on paper by Lebret, Collobert, 2015
Home-page: https://github.com/shashankg7/WordEmbeddingAutoencoder
Author: Muktabh Mayank, Shashank gupta
Author-email: muktabh@paralleldots.com,  h20104198@pilani.bits-pilani.ac.in
License: MIT
Platform: UNKNOWN
Classifier: Development Status :: 3 - Alpha
Classifier: License :: OSI Approved :: MIT License
Classifier: Topic :: Scientific/Engineering :: Artificial Intelligence
